mcu_tcp_impl/__init__.py
mcu_tcp_impl/mcu_client.py
mcu_tcp_impl/mcu_server.py
mcu_tcp_impl/server_api.py
mcu_communication_tcp-1.0.2.dist-info/METADATA
mcu_communication_tcp-1.0.2.dist-info/WHEEL
mcu_communication_tcp-1.0.2.dist-info/top_level.txt
mcu_communication_tcp-1.0.2.dist-info/RECORD
